<annotation>
	<folder>gun</folder>
	<filename>armas (431).jpg</filename>
	<path>demo/gun\armas (431).jpg</path>
	<source>
		<database>Unknown</database>
	</source>
	<size>
		<width>168</width>
		<height>112</height>
		<depth>3</depth>
	</size>
	<segmented>0</segmented>
	<object>
		<name>gun</name>
		<pose>Unspecified</pose>
		<truncated>0</truncated>
		<difficult>0</difficult>
		<bndbox>
			<xmin>13</xmin>
			<ymin>18</ymin>
			<xmax>122</xmax>
			<ymax>90</ymax>
		</bndbox>
	</object>
</annotation>
