<annotation>
	<folder>gun</folder>
	<filename>armas (1330).jpg</filename>
	<path>demo/gun\armas (1330).jpg</path>
	<source>
		<database>Unknown</database>
	</source>
	<size>
		<width>570</width>
		<height>415</height>
		<depth>3</depth>
	</size>
	<segmented>0</segmented>
	<object>
		<name>gun</name>
		<pose>Unspecified</pose>
		<truncated>0</truncated>
		<difficult>0</difficult>
		<bndbox>
			<xmin>4</xmin>
			<ymin>55</ymin>
			<xmax>564</xmax>
			<ymax>395</ymax>
		</bndbox>
	</object>
</annotation>
