<annotation>
  <folder>laptop_img</folder>
  <filename>handlapv1_1885.png</filename>
  <path>./laptop_img</path>
  <source>
    <database>Unknown</database>
  </source>
  <size>
    <width>832</width>
    <height>480</height>
    <depth>3</depth>
  </size>
  <segmented>0</segmented>
  <object>
    <name>person</name>
    <pose>Unspecified</pose>
    <truncated>0</truncated>
    <difficult>0</difficult>
    <bndbox>
      <xmin>303</xmin>
      <ymin>133</ymin>
      <xmax>711</xmax>
      <ymax>479</ymax>
    </bndbox>
  </object>
  <object>
    <name>hand</name>
    <pose>Unspecified</pose>
    <truncated>0</truncated>
    <difficult>0</difficult>
    <bndbox>
      <xmin>628</xmin>
      <ymin>75</ymin>
      <xmax>694</xmax>
      <ymax>324</ymax>
    </bndbox>
  </object>
  <object>
    <name>redscarf</name>
    <pose>Unspecified</pose>
    <truncated>0</truncated>
    <difficult>0</difficult>
    <bndbox>
      <xmin>468</xmin>
      <ymin>306</ymin>
      <xmax>537</xmax>
      <ymax>420</ymax>
    </bndbox>
  </object>
</annotation>